niftyTradeCalendar/__init__.py
niftyTradeCalendar/main.py
niftyTradeCalendar/data/__init__.py
niftyTradeCalendar/data/holidays.py
niftyTradeCalendar/utils/__init__.py
niftyTradeCalendar/utils/dates.py
niftyTradeCalendar-0.3.0.dist-info/LICENSE
niftyTradeCalendar-0.3.0.dist-info/METADATA
niftyTradeCalendar-0.3.0.dist-info/WHEEL
niftyTradeCalendar-0.3.0.dist-info/top_level.txt
niftyTradeCalendar-0.3.0.dist-info/RECORD
