Metadata-Version: 2.1
Name: niftyTradeCalendar
Version: 0.3.0
Summary: Holiday and Trading Day Calendar for NIFTY
Home-page: https://github.com/skrdeveloper1/niftyTradeCalendar
Author: Sonu Kumar
Author-email: skrdeveloper1@gmail.com
License: UNKNOWN
Project-URL: LinkedIn, https://in.linkedin.com/in/skrdeveloper1
Project-URL: GitHub, https://github.com/skrdeveloper1/niftyTradeCalendar
Platform: UNKNOWN
Classifier: Programming Language :: Python :: 3
Classifier: Operating System :: OS Independent
Requires-Python: >=3.6
